[
  {
    "id": 145930,
    "type": "folder"
  },
  {
    "id": 145931,
    "type": "folder",
    "parentId": 145930
  },
  {
    "id": 777432,
    "type": "file",
    "parentId": 145951
  },
  {
    "id": 145932,
    "type": "folder",
    "parentId": 145930
  },
  {
    "id": 145941,
    "type": "folder",
    "parentId": 145931
  },
  {
    "id": 145942,
    "type": "folder",
    "parentId": 145931
  },
  {
    "id": 245950,
    "type": "file",
    "parentId": 145932
  },
  {
    "id": 445950,
    "type": "file",
    "parentId": 245950
  },
  {
    "id": 145950,
    "type": "folder",
    "parentId": 145932
  },
  {
    "id": 145951,
    "type": "folder",
    "parentId": 145932
  },
  {
    "id": 545260,
    "type": "file",
    "parentId": 145930
  },
  {
    "id": 175440,
    "type": "file",
    "parentId": 145940
  },
  {
    "id": 145970,
    "type": "folder",
    "parentId": 145960
  },
  {
    "id": 145980,
    "type": "folder",
    "parentId": 145970
  },
  {
    "id": 161448,
    "type": "file",
    "parentId": 145980
  },
  {
    "id": 161449,
    "type": "file",
    "parentId": 145980
  },
  {
    "id": 161447,
    "type": "file",
    "parentId": 145980
  },
  {
    "id": 145110,
    "type": "folder",
    "parentId": 145950
  },
  {
    "id": 145120,
    "type": "folder",
    "parentId": 145110
  },
  {
    "id": 145130,
    "type": "folder",
    "parentId": 145120
  },
  {
    "id": 999999,
    "type": "file",
    "parentId": 145140
  },
  {
    "id": 145140,
    "type": "folder",
    "parentId": 145130
  },
  {
    "id": 145220,
    "type": "folder",
    "parentId": 145120
  },
  {
    "id": 777970,
    "type": "file",
    "parentId": 145960
  },
  {
    "id": 145940,
    "type": "folder",
    "parentId": 145931
  },
  {
    "id": 145960,
    "type": "folder",
    "parentId": 145941
  }
]